epigeec_ihecdata/__init__.py
epigeec_ihecdata/ihecdata.py
epigeec_ihecdata/ihecdatasource.py
epigeec_ihecdata-0.1.0.dist-info/LICENSE
epigeec_ihecdata-0.1.0.dist-info/METADATA
epigeec_ihecdata-0.1.0.dist-info/WHEEL
epigeec_ihecdata-0.1.0.dist-info/top_level.txt
epigeec_ihecdata-0.1.0.dist-info/RECORD
