Metadata-Version: 2.1
Name: epigeec-ihecdata
Version: 0.1.0
Summary: A generic way to manage ihecdata cached on Calcul Québec repositories.
Home-page: https://gitlab.com/labjacquespe/epigeec_ihecdata/tree/master
Author: Simon Hébert-Deschamps
Author-email: simon.hebert-deschamps@usherbrooke.ca
License: ECL
Platform: UNKNOWN
Classifier: Operating System :: OS Independent
Classifier: Programming Language :: Python
Classifier: License :: OSI Approved :: GNU General Public License v3 (GPLv3)
Classifier: Topic :: Scientific/Engineering :: Bio-Informatics
Classifier: Intended Audience :: Science/Research
Classifier: Environment :: Console
Requires-Python: >=2.7.5, !=3.0.*, !=3.1.*, !=3.2.*, !=3.3.*, !=3.4.*, <4
